causalimpact/__init__.py
causalimpact/__version__.py
causalimpact/inferences.py
causalimpact/main.py
causalimpact/misc.py
causalimpact/plot.py
causalimpact/summary.py
causalimpact/templates/report
causalimpact/templates/summary
pycausalimpact-0.1.1.dist-info/LICENSE
pycausalimpact-0.1.1.dist-info/METADATA
pycausalimpact-0.1.1.dist-info/WHEEL
pycausalimpact-0.1.1.dist-info/top_level.txt
pycausalimpact-0.1.1.dist-info/RECORD
