Metadata-Version: 2.1
Name: pycausalimpact
Version: 0.1.1
Summary: Python version of Google's Causal Impact model
Home-page: https://github.com/dafiti/causalimpact
Author: Willian Fuks
Author-email: willian.fuks@gmail.com
License: MIT
Platform: UNKNOWN
Classifier: Development Status :: 4 - Beta
Classifier: Environment :: Console
Classifier: Intended Audience :: Developers
Classifier: Intended Audience :: Science/Research
Classifier: License :: OSI Approved :: Apache Software License
Classifier: Natural Language :: English
Classifier: Operating System :: Unix
Classifier: Programming Language :: Python :: 3.6
Classifier: Programming Language :: Python :: 3.7
Classifier: Programming Language :: Python :: 3.8
Classifier: Programming Language :: Python :: Implementation :: CPython
Classifier: Topic :: Scientific/Engineering
Provides-Extra: docs
Provides-Extra: testing
